pingverter/__init__.py
pingverter/cerulean_class.py
pingverter/converter.py
pingverter/garmin_class.py
pingverter/humminbird_class.py
pingverter/lowrance_class.py
pingverter/lowrance_class_archive.py
pingverter/sonar_class.py
pingverter/version.py
pingverter/verter_utils.py
pingverter-2.0.9.dist-info/licenses/LICENSE
pingverter-2.0.9.dist-info/METADATA
pingverter-2.0.9.dist-info/WHEEL
pingverter-2.0.9.dist-info/top_level.txt
pingverter-2.0.9.dist-info/RECORD
