Metadata-Version: 2.4
Name: pingverter
Version: 2.0.9
Summary: A Python-based converter for sonar logs used by PINGMapper
Author: Cameron Bodine
Author-email: bodine.cs@gmail.email
Keywords: pingmapper,sonar,ecology,remotesensing,sidescan,sidescan-sonar,aquatic,humminbird,lowrance,gis,oceanography,limnology
Classifier: Development Status :: 3 - Alpha
Classifier: Programming Language :: Python :: 3
Classifier: License :: OSI Approved :: MIT License
Classifier: Operating System :: OS Independent
Classifier: Topic :: Scientific/Engineering
Classifier: Topic :: Scientific/Engineering :: Visualization
Classifier: Topic :: Scientific/Engineering :: Oceanography
Classifier: Topic :: Scientific/Engineering :: GIS
Classifier: Topic :: Scientific/Engineering :: Hydrology
Requires-Python: >=3.6
License-File: LICENSE
Requires-Dist: numpy
Requires-Dist: pandas
Requires-Dist: pyproj
Requires-Dist: joblib
Dynamic: author
Dynamic: author-email
Dynamic: classifier
Dynamic: description
Dynamic: description-content-type
Dynamic: keywords
Dynamic: license-file
Dynamic: requires-dist
Dynamic: requires-python
Dynamic: summary
